didymus/__about__.py
didymus/__init__.py
didymus-0.0.0.dist-info/METADATA
didymus-0.0.0.dist-info/WHEEL
didymus-0.0.0.dist-info/licenses/LICENSE
didymus-0.0.0.dist-info/RECORD
