Metadata-Version: 2.1
Name: didymus
Version: 0.0.0
Summary: Pebble packing and movement tool
Author-email: Zoe Richter <zoerichter96@gmail.com>
License: BSD 3-Clause License
License-File: LICENSE
Requires-Python: >=3.8
